rewindlearn/__init__.py
rewindlearn/__main__.py
rewindlearn/py.typed
rewindlearn/chains/__init__.py
rewindlearn/chains/actions.py
rewindlearn/chains/base.py
rewindlearn/chains/chunks.py
rewindlearn/chains/coverage.py
rewindlearn/chains/friction.py
rewindlearn/chains/resources.py
rewindlearn/chains/summary.py
rewindlearn/chains/timeline.py
rewindlearn/cli/__init__.py
rewindlearn/cli/main.py
rewindlearn/cli/commands/__init__.py
rewindlearn/cli/commands/config.py
rewindlearn/cli/commands/process.py
rewindlearn/cli/commands/template.py
rewindlearn/core/__init__.py
rewindlearn/core/config.py
rewindlearn/core/exceptions.py
rewindlearn/core/logging.py
rewindlearn/llm/__init__.py
rewindlearn/llm/providers.py
rewindlearn/llm/router.py
rewindlearn/output/__init__.py
rewindlearn/output/builder.py
rewindlearn/processors/__init__.py
rewindlearn/processors/base.py
rewindlearn/processors/chat.py
rewindlearn/processors/transcript.py
rewindlearn/templates/__init__.py
rewindlearn/templates/loader.py
rewindlearn/templates/models.py
rewindlearn/workflow/__init__.py
rewindlearn/workflow/executor.py
rewindlearn/workflow/graph.py
rewindlearn/workflow/state.py
rewindlearn-0.1.1.dist-info/METADATA
rewindlearn-0.1.1.dist-info/WHEEL
rewindlearn-0.1.1.dist-info/entry_points.txt
rewindlearn-0.1.1.dist-info/licenses/LICENSE
rewindlearn-0.1.1.dist-info/RECORD
