Metadata-Version: 2.4
Name: rewindlearn
Version: 0.1.1
Summary: Transform session artifacts into structured knowledge
Project-URL: Homepage, https://github.com/knightsri/rewind.learn
Project-URL: Documentation, https://rewindlearn.readthedocs.io
Project-URL: Repository, https://github.com/knightsri/rewind.learn
Project-URL: Issues, https://github.com/knightsri/rewind.learn/issues
Project-URL: Changelog, https://github.com/knightsri/rewind.learn/blob/main/CHANGELOG.md
Author-email: Sri Bolisetty <sri@example.com>
License-Expression: Apache-2.0
License-File: LICENSE
Keywords: ai,education,langchain,learning,llm,transcription
Classifier: Development Status :: 3 - Alpha
Classifier: Environment :: Console
Classifier: Intended Audience :: Developers
Classifier: Intended Audience :: Education
Classifier: License :: OSI Approved :: Apache Software License
Classifier: Programming Language :: Python :: 3.10
Classifier: Programming Language :: Python :: 3.11
Classifier: Programming Language :: Python :: 3.12
Classifier: Topic :: Education
Classifier: Topic :: Text Processing :: Linguistic
Classifier: Typing :: Typed
Requires-Python: >=3.10
Requires-Dist: langchain-anthropic>=0.3
Requires-Dist: langchain-openai>=0.2
Requires-Dist: langchain>=0.3
Requires-Dist: langgraph>=0.2
Requires-Dist: langsmith>=0.1
Requires-Dist: pydantic-settings>=2.0
Requires-Dist: pydantic>=2.0
Requires-Dist: python-dotenv>=1.0
Requires-Dist: pyyaml>=6.0
Requires-Dist: rich>=13.0
Requires-Dist: typer[all]>=0.12
Requires-Dist: webvtt-py>=0.5
Provides-Extra: dev
Requires-Dist: black>=24.0; extra == 'dev'
Requires-Dist: mypy>=1.10; extra == 'dev'
Requires-Dist: pre-commit>=3.0; extra == 'dev'
Requires-Dist: pytest-asyncio>=0.23; extra == 'dev'
Requires-Dist: pytest-cov>=5.0; extra == 'dev'
Requires-Dist: pytest>=8.0; extra == 'dev'
Requires-Dist: ruff>=0.4; extra == 'dev'
Provides-Extra: docs
Requires-Dist: mkdocs-material>=9.5; extra == 'docs'
Requires-Dist: mkdocs>=1.6; extra == 'docs'
Requires-Dist: mkdocstrings[python]>=0.25; extra == 'docs'
Provides-Extra: examples
Requires-Dist: ffmpeg-python>=0.2; extra == 'examples'
Requires-Dist: pymupdf>=1.24; extra == 'examples'
Requires-Dist: weasyprint>=62; extra == 'examples'
